{
  "version": "7",
  "dialect": "postgresql",
  "entries": [
    {
      "idx": 0,
      "version": "7",
      "when": 1750834209730,
      "tag": "0000_damp_gorgon",
      "breakpoints": true
    },
    {
      "idx": 1,
      "version": "7",
      "when": 1750880134303,
      "tag": "0001_funny_the_watchers",
      "breakpoints": true
    },
    {
      "idx": 2,
      "version": "7",
      "when": 1750880242682,
      "tag": "0002_bumpy_makkari",
      "breakpoints": true
    },
    {
      "idx": 3,
      "version": "7",
      "when": 1750880394615,
      "tag": "0003_warm_wind_dancer",
      "breakpoints": true
    },
    {
      "idx": 4,
      "version": "7",
      "when": 1750892148338,
      "tag": "0004_fresh_changeling",
      "breakpoints": true
    }
  ]
}
